xaal/__init__.py
xaal/monitor/__init__.py
xaal/monitor/__main__.py
xaal/monitor/example.py
xaal/monitor/monitor.py
xaal_monitor-0.5.2.dist-info/METADATA
xaal_monitor-0.5.2.dist-info/WHEEL
xaal_monitor-0.5.2.dist-info/top_level.txt
xaal_monitor-0.5.2.dist-info/RECORD
